usdm4_m11/__info__.py
usdm4_m11/__init__.py
usdm4_m11/data/mapping/title_page_mapping.yaml
usdm4_m11/data/specification/sections.yaml
usdm4_m11/data/specification/elements/title_page_elements.yaml
usdm4_m11/data/specification/templates/title_page_template.html
usdm4_m11/data_view/__init__.py
usdm4_m11/data_view/data_view.py
usdm4_m11/document_view/__init__.py
usdm4_m11/document_view/document_view.py
usdm4_m11/elements/__init__.py
usdm4_m11/elements/elements.py
usdm4_m11/export/__init__.py
usdm4_m11/export/m11_export.py
usdm4_m11/import_/__init__.py
usdm4_m11/import_/m11_amendment.py
usdm4_m11/import_/m11_estimands.py
usdm4_m11/import_/m11_import.py
usdm4_m11/import_/m11_inclusion_exclusion.py
usdm4_m11/import_/m11_miscellaneous.py
usdm4_m11/import_/m11_sections.py
usdm4_m11/import_/m11_styles.py
usdm4_m11/import_/m11_title_page.py
usdm4_m11/import_/m11_to_usdm.py
usdm4_m11/import_/m11_utility.py
usdm4_m11/import_/assemble/__init__.py
usdm4_m11/import_/extract/__init__.py
usdm4_m11/import_/extract/amendments.py
usdm4_m11/import_/extract/document.py
usdm4_m11/import_/extract/inclusion_exclusion.py
usdm4_m11/import_/extract/title_page.py
usdm4_m11/import_/extract/utility.py
usdm4_m11/import_/load/__init__.py
usdm4_m11/specification/__init__.py
usdm4_m11/specification/files.py
usdm4_m11/specification/section.py
usdm4_m11/specification/sections.py
usdm4_m11/utility/__init__.py
usdm4_m11/utility/soup.py
usdm4_m11-0.8.1.dist-info/METADATA
usdm4_m11-0.8.1.dist-info/WHEEL
usdm4_m11-0.8.1.dist-info/top_level.txt
usdm4_m11-0.8.1.dist-info/RECORD
