Metadata-Version: 2.4
Name: usdm4_m11
Version: 0.8.1
Summary: A package for processing M11 protocol documents and converting them to USDM format
Author: D Iberson-Hurst
Author-email: 
Classifier: Intended Audience :: Developers
Classifier: Programming Language :: Python
Classifier: Programming Language :: Python :: 3
Classifier: Programming Language :: Python :: 3.12
Classifier: Operating System :: OS Independent
Requires-Python: >=3.12
Requires-Dist: usdm4>=0.14.0
Requires-Dist: raw_docx>=0.11.0
Requires-Dist: usdm4_cpt>=0.5.0
Dynamic: author
Dynamic: classifier
Dynamic: description
Dynamic: description-content-type
Dynamic: requires-dist
Dynamic: requires-python
Dynamic: summary
